docs_conf/__init__.py
docs_conf/conf.py
docs_conf/defaults/default.yaml
docs_conf/defaults/lfdocs.yaml
docs_conf/defaults/onap.yaml
docs_conf/defaults/opendaylight.yaml
docs_conf/defaults/opnfv.yaml
docs_conf/defaults/oran.yaml
lfdocs_conf-0.10.0.dist-info/licenses/AUTHORS
lfdocs_conf-0.10.0.dist-info/METADATA
lfdocs_conf-0.10.0.dist-info/WHEEL
lfdocs_conf-0.10.0.dist-info/pbr.json
lfdocs_conf-0.10.0.dist-info/top_level.txt
lfdocs_conf-0.10.0.dist-info/RECORD
