Metadata-Version: 2.4
Name: lfdocs_conf
Version: 0.10.0
Summary: Linux Foundation DocsConf
Home-page: https://docs.releng.linuxfoundation.org/projects/lfdocs-conf
Author: Linux Foundation Releng
Author-email: releng@linuxfoundation.org
License: EPL-1.0
Project-URL: Bug Tracker, https://jira.linuxfoundation.org
Project-URL: Documentation, https://docs.releng.linuxfoundation.org/projects/lfdocs-conf
Project-URL: Source Code, https://github.com/lfit/releng-docs-conf
Classifier: Intended Audience :: Developers
Classifier: Intended Audience :: Information Technology
Classifier: License :: OSI Approved :: Eclipse Public License 1.0 (EPL-1.0)
Classifier: Operating System :: OS Independent
Classifier: Programming Language :: Python
License-File: AUTHORS
Requires-Dist: PyYAML
Requires-Dist: Sphinx<9.0.0,>=4.2.0
Requires-Dist: sphinx_bootstrap_theme
Requires-Dist: sphinx-tabs
Requires-Dist: sphinxcontrib-blockdiag
Requires-Dist: sphinxcontrib-needs
Requires-Dist: sphinxcontrib.plantuml
Requires-Dist: sphinxcontrib-nwdiag
Requires-Dist: sphinxcontrib-seqdiag
Requires-Dist: sphinxcontrib-swaggerdoc
Requires-Dist: sphinx-rtd-theme
Requires-Dist: funcparserlib>=1.0.0a0
Dynamic: author
Dynamic: author-email
Dynamic: classifier
Dynamic: description
Dynamic: description-content-type
Dynamic: home-page
Dynamic: license
Dynamic: license-file
Dynamic: project-url
Dynamic: requires-dist
Dynamic: summary
